kadaptest5/__init__.py
kadaptest5/data.py
kadaptest5/vin_decoder/__init__.py
kadaptest5/vin_decoder/decoder.py
kadaptest5-0.0.1.dist-info/LICENSE
kadaptest5-0.0.1.dist-info/METADATA
kadaptest5-0.0.1.dist-info/WHEEL
kadaptest5-0.0.1.dist-info/top_level.txt
kadaptest5-0.0.1.dist-info/RECORD
